Metadata-Version: 1.0
Name: brainart
Version: 1.0.9
Summary: make images out of brain imaging data
Home-page: http://www.github.com/vsoch/brainart
Author: vsoch
Author-email: vsochat@stanford.edu
License: LICENSE
Keywords: brain art neuroimaging
Platform: UNKNOWN
